mymlp/softmax8.v
module softmax8 #(
    parameter DATA_WIDTH = 8,
    parameter NODES = 387
)(
    input clk,
    input reset,
    input [DATA_WIDTH*NODES-1:0] inputs,
    output reg [DATA_WIDTH*NODES-1:0] outputs, // Q0.8定点概率
    output reg done
);

    // 内部寄存器
    reg [DATA_WIDTH-1:0] input_array [0:NODES-1];
    reg [15:0] exp_array [0:NODES-1];      // 存储指数结果
    reg [23:0] exp_sum;                    // 累加所有指数
    reg [8:0] idx;
    reg [2:0] state;

    // 指数查找表
    function [15:0] exp_lut;
        input signed [7:0] x;
        reg [7:0] abs_x;
        reg [15:0] lut [0:8];
        begin
            lut[0]=16'd256;    // exp(0) * 256
            lut[1]=16'd696;    // exp(1) * 256
            lut[2]=16'd1871;   // exp(2) * 256
            lut[3]=16'd5041;   // exp(3) * 256
            lut[4]=16'd13623;  // exp(4) * 256
            lut[5]=16'd36887;  // exp(5) * 256
            lut[6]=16'd99999;  // exp(6) * 256
            lut[7]=16'd271828; // exp(7) * 256
            lut[8]=16'd738905; // exp(8) * 256
            abs_x = (x < 0) ? -x : x;
            if (x < -8)
                exp_lut = 16'd1; // exp(-大数)≈0
            else if (x > 8)
                exp_lut = lut[8]; // exp(大数)≈exp(8)
            else if (x < 0)
                exp_lut = 16'd65536 / lut[abs_x]; // 近似exp(-x)=1/exp(x)
            else
                exp_lut = lut[abs_x];
        end
    endfunction

    // 状态机
    localparam S_IDLE = 0, S_EXP = 1, S_SUM = 2, S_DIV = 3, S_DONE = 4;

    integer i;

    always @(posedge clk or posedge reset) begin
        if (reset) begin
            idx <= 0;
            state <= S_IDLE;
            exp_sum <= 0;
            done <= 0;
        end else begin
            case (state)
                S_IDLE: begin
                    for (i = 0; i < NODES; i = i + 1)
                        input_array[i] <= inputs[DATA_WIDTH*i +: DATA_WIDTH];
                    idx <= 0;
                    exp_sum <= 0;
                    done <= 0;
                    state <= S_EXP;
                end
                S_EXP: begin
                    exp_array[idx] <= exp_lut(input_array[idx]);
                    idx <= idx + 1;
                    if (idx == NODES-1) begin
                        idx <= 0;
                        state <= S_SUM;
                    end
                end
                S_SUM: begin
                    exp_sum <= 0;
                    for (i = 0; i < NODES; i = i + 1)
                        exp_sum <= exp_sum + exp_array[i];
                    idx <= 0;
                    state <= S_DIV;
                end
                S_DIV: begin
                    for (i = 0; i < NODES; i = i + 1) begin
                        // Q0.8定点概率输出
                        if (exp_sum != 0)
                            outputs[DATA_WIDTH*i +: DATA_WIDTH] <= (exp_array[i] << 8) / exp_sum;
                        else
                            outputs[DATA_WIDTH*i +: DATA_WIDTH] <= 0;
                    end
                    state <= S_DONE;
                end
                S_DONE: begin
                    done <= 1;
                end
            endcase
        end
    end

endmodule

mymlp/softmax8_tb.v
`timescale 1ns/1ps

module softmax8_tb;

    parameter DATA_WIDTH = 8;
    parameter NODES = 8; // 便于观察

    reg clk;
    reg reset;
    reg [DATA_WIDTH*NODES-1:0] inputs;
    wire [DATA_WIDTH*NODES-1:0] outputs;
    wire done;

    // 实例化 softmax8
    softmax8 #(
        .DATA_WIDTH(DATA_WIDTH),
        .NODES(NODES)
    ) dut (
        .clk(clk),
        .reset(reset),
        .inputs(inputs),
        .outputs(outputs),
        .done(done)
    );

    // 时钟生成
    initial clk = 0;
    always #5 clk = ~clk;

    integer i;

    initial begin
        $dumpfile("softmax8_tb.vcd");
        $dumpvars(0, softmax8_tb);

        // 初始化
        reset = 1;
        inputs = 0;
        #20;
        reset = 0;

        // 输入一组简单数据
        // 比如输入 1,2,3,4,5,6,7,8
        for (i = 0; i < NODES; i = i + 1)
            inputs[DATA_WIDTH*i +: DATA_WIDTH] = i + 1;

        #10;

        // 等待 done 信号
        wait(done);

        // 打印输出（Q0.8定点，除以256得到概率）
        $display("Softmax outputs (Q0.8):");
        for (i = 0; i < NODES; i = i + 1)
            $display("outputs[%0d] = %0d (prob = %f)", i, outputs[DATA_WIDTH*i +: DATA_WIDTH], outputs[DATA_WIDTH*i +: DATA_WIDTH]/256.0);

        #20;
        $finish;
    end

endmodule

mymlp/softmax8_tb.vcd
$date
	Thu Jun 19 21:52:15 2025
$end
$version
	Icarus Verilog
$end
$timescale
	1ps
$end
$scope module softmax8_tb $end
$var wire 64 ! outputs [63:0] $end
$var wire 1 " done $end
$var parameter 32 # DATA_WIDTH $end
$var parameter 32 $ NODES $end
$var reg 1 % clk $end
$var reg 64 & inputs [63:0] $end
$var reg 1 ' reset $end
$var integer 32 ( i [31:0] $end
$scope module dut $end
$var wire 1 % clk $end
$var wire 64 ) inputs [63:0] $end
$var wire 1 ' reset $end
$var parameter 32 * DATA_WIDTH $end
$var parameter 32 + NODES $end
$var parameter 32 , S_DIV $end
$var parameter 32 - S_DONE $end
$var parameter 32 . S_EXP $end
$var parameter 32 / S_IDLE $end
$var parameter 32 0 S_SUM $end
$var reg 1 " done $end
$var reg 24 1 exp_sum [23:0] $end
$var reg 9 2 idx [8:0] $end
$var reg 64 3 outputs [63:0] $end
$var reg 3 4 state [2:0] $end
$var integer 32 5 i [31:0] $end
$scope function exp_lut $end
$var reg 8 6 abs_x [7:0] $end
$var reg 8 7 x [7:0] $end
$upscope $end
$upscope $end
$upscope $end
$enddefinitions $end
$comment Show the parameter values. $end
$dumpall
b10 0
b0 /
b1 .
b100 -
b11 ,
b1000 +
b1000 *
b1000 $
b1000 #
$end
#0
$dumpvars
bx 7
bx 6
bx 5
b0 4
bx 3
b0 2
b0 1
b0 )
bx (
1'
b0 &
0%
0"
bx !
$end
#5000
1%
#10000
0%
#15000
1%
#20000
0%
b100000000111000001100000010100000100000000110000001000000001 &
b100000000111000001100000010100000100000000110000001000000001 )
b1000 (
0'
#25000
b1 4
b1000 5
1%
#30000
0%
#35000
b1 2
b1 6
b1 7
1%
#40000
0%
#45000
b10 2
b10 6
b10 7
1%
#50000
0%
#55000
b11 2
b11 6
b11 7
1%
#60000
0%
#65000
b100 2
b100 6
b100 7
1%
#70000
0%
#75000
b101 2
b101 6
b101 7
1%
#80000
0%
#85000
b110 2
b110 6
b110 7
1%
#90000
0%
#95000
b111 2
b111 6
b111 7
1%
#100000
0%
#105000
b10 4
b0 2
b1000 6
b1000 7
1%
#110000
0%
#115000
b11 4
b100011001011001 1
b1000 5
1%
#120000
0%
#125000
b100 4
b10001001111010010000110011000001010001110001101000001001 !
b10001001111010010000110011000001010001110001101000001001 3
b1000 5
1%
#130000
0%
#135000
b1000 (
1"
1%
